jspaste/__init__.py
tests/__init__.py
tests/test_jspaste.py
jspaste-0.0.1.dist-info/LICENSE
jspaste-0.0.1.dist-info/METADATA
jspaste-0.0.1.dist-info/WHEEL
jspaste-0.0.1.dist-info/top_level.txt
jspaste-0.0.1.dist-info/RECORD
